onwords/__init__.py
onwords/api.py
onwords/cli.py
onwords/controller.py
onwords-0.2.0.dist-info/licenses/LICENSE
onwords-0.2.0.dist-info/METADATA
onwords-0.2.0.dist-info/WHEEL
onwords-0.2.0.dist-info/entry_points.txt
onwords-0.2.0.dist-info/top_level.txt
onwords-0.2.0.dist-info/RECORD
