Metadata-Version: 2.4
Name: onwords
Version: 0.2.0
Summary: Onwords - Gate Control Package for Smart Gate Systems
Author-email: Onwords <contact@onwords.in>
Maintainer-email: Onwords Team <dev@onwords.in>
License: MIT
Project-URL: Homepage, https://onwords.in
Project-URL: Documentation, https://docs.onwords.in
Project-URL: Repository, https://github.com/onwords/onwords-python
Project-URL: Issues, https://github.com/onwords/onwords-python/issues
Keywords: iot,smart-home,gate-control,sliding-gate,arm-gate,onwords,home-automation
Classifier: Development Status :: 4 - Beta
Classifier: Intended Audience :: Developers
Classifier: License :: OSI Approved :: MIT License
Classifier: Operating System :: OS Independent
Classifier: Programming Language :: Python :: 3
Classifier: Programming Language :: Python :: 3.8
Classifier: Programming Language :: Python :: 3.9
Classifier: Programming Language :: Python :: 3.10
Classifier: Programming Language :: Python :: 3.11
Classifier: Programming Language :: Python :: 3.12
Classifier: Topic :: Home Automation
Classifier: Topic :: Software Development :: Libraries :: Python Modules
Requires-Python: >=3.8
License-File: LICENSE
Provides-Extra: mqtt
Requires-Dist: paho-mqtt>=1.6.0; extra == "mqtt"
Provides-Extra: dev
Requires-Dist: pytest>=7.0; extra == "dev"
Requires-Dist: pytest-cov>=4.0; extra == "dev"
Requires-Dist: black>=23.0; extra == "dev"
Requires-Dist: mypy>=1.0; extra == "dev"
Dynamic: license-file
